[
    {
        "id": 1,
        "seek": 2776,
        "start": 0.0,
        "end": 4.86,
        "text": " hello hello you've reached Vibha Jan Miller I'm sorry I can't take your call",
        "tokens": [
            50363,
            23748,
            23748,
            345,
            1053,
            4251,
            569,
            571,
            3099,
            2365,
            7920,
            314,
            1101,
            7926,
            314,
            460,
            470,
            1011,
            534,
            869,
            50606
        ],
        "temperature": 0.0,
        "avg_logprob": -0.22944121719688498,
        "compression_ratio": 1.6261261261261262,
        "no_speech_prob": 0.7223988771438599,
        "words": null
    },
    {
        "id": 2,
        "seek": 2776,
        "start": 4.86,
        "end": 8.64,
        "text": " if you'd like to leave a message I'll get back to you as soon as possible",
        "tokens": [
            50606,
            611,
            345,
            1549,
            588,
            284,
            2666,
            257,
            3275,
            314,
            1183,
            651,
            736,
            284,
            345,
            355,
            2582,
            355,
            1744,
            50795
        ],
        "temperature": 0.0,
        "avg_logprob": -0.22944121719688498,
        "compression_ratio": 1.6261261261261262,
        "no_speech_prob": 0.7223988771438599,
        "words": null
    },
    {
        "id": 3,
        "seek": 2776,
        "start": 8.64,
        "end": 15.0,
        "text": " thank you at the tone please record your message when you finish recording",
        "tokens": [
            50795,
            5875,
            345,
            379,
            262,
            8216,
            3387,
            1700,
            534,
            3275,
            618,
            345,
            5461,
            8296,
            51113
        ],
        "temperature": 0.0,
        "avg_logprob": -0.22944121719688498,
        "compression_ratio": 1.6261261261261262,
        "no_speech_prob": 0.7223988771438599,
        "words": null
    },
    {
        "id": 4,
        "seek": 2776,
        "start": 15.0,
        "end": 20.92,
        "text": " you may hang up or press 1 for more options hi Vibha I just got your",
        "tokens": [
            51113,
            345,
            743,
            8181,
            510,
            393,
            1803,
            352,
            329,
            517,
            3689,
            23105,
            569,
            571,
            3099,
            314,
            655,
            1392,
            534,
            51409
        ],
        "temperature": 0.0,
        "avg_logprob": -0.22944121719688498,
        "compression_ratio": 1.6261261261261262,
        "no_speech_prob": 0.7223988771438599,
        "words": null
    },
    {
        "id": 5,
        "seek": 2776,
        "start": 20.92,
        "end": 27.76,
        "text": " resume so may I know your yearly salary expectations so that I can",
        "tokens": [
            51409,
            15294,
            523,
            743,
            314,
            760,
            534,
            24169,
            9588,
            9027,
            523,
            326,
            314,
            460,
            51751
        ],
        "temperature": 0.0,
        "avg_logprob": -0.22944121719688498,
        "compression_ratio": 1.6261261261261262,
        "no_speech_prob": 0.7223988771438599,
        "words": null
    },
    {
        "id": 6,
        "seek": 4550,
        "start": 27.76,
        "end": 33.04,
        "text": " just send you the RTR and you can confirm it and after that I will submit",
        "tokens": [
            50363,
            655,
            3758,
            345,
            262,
            371,
            5446,
            290,
            345,
            460,
            6216,
            340,
            290,
            706,
            326,
            314,
            481,
            9199,
            50627
        ],
        "temperature": 0.0,
        "avg_logprob": -0.20791300820807615,
        "compression_ratio": 1.5,
        "no_speech_prob": 0.17402012646198273,
        "words": null
    },
    {
        "id": 7,
        "seek": 4550,
        "start": 33.04,
        "end": 40.68,
        "text": " your profile so please share your salary expectations so that I can share you",
        "tokens": [
            50627,
            534,
            7034,
            523,
            3387,
            2648,
            534,
            9588,
            9027,
            523,
            326,
            314,
            460,
            2648,
            345,
            51009
        ],
        "temperature": 0.0,
        "avg_logprob": -0.20791300820807615,
        "compression_ratio": 1.5,
        "no_speech_prob": 0.17402012646198273,
        "words": null
    },
    {
        "id": 8,
        "seek": 4550,
        "start": 40.68,
        "end": 45.2,
        "text": " the RTR thank you and have a nice day",
        "tokens": [
            51009,
            262,
            371,
            5446,
            5875,
            345,
            290,
            423,
            257,
            3621,
            1110,
            51235
        ],
        "temperature": 0.0,
        "avg_logprob": -0.20791300820807615,
        "compression_ratio": 1.5,
        "no_speech_prob": 0.17402012646198273,
        "words" : null
    }
]